{
  "db_name": "PostgreSQL",
  "query": "SELECT id, device_code_hash, user_code, client_id, scopes, user_id, status, interval, expires_at, last_polled_at, created_at FROM yauth_device_codes WHERE user_code = $1 AND status = 'pending' AND expires_at > $2",
  "describe": {
    "columns": [
      {
        "ordinal": 0,
        "name": "id",
        "type_info": "Uuid"
      },
      {
        "ordinal": 1,
        "name": "device_code_hash",
        "type_info": "Varchar"
      },
      {
        "ordinal": 2,
        "name": "user_code",
        "type_info": "Varchar"
      },
      {
        "ordinal": 3,
        "name": "client_id",
        "type_info": "Varchar"
      },
      {
        "ordinal": 4,
        "name": "scopes",
        "type_info": "Jsonb"
      },
      {
        "ordinal": 5,
        "name": "user_id",
        "type_info": "Uuid"
      },
      {
        "ordinal": 6,
        "name": "status",
        "type_info": "Varchar"
      },
      {
        "ordinal": 7,
        "name": "interval",
        "type_info": "Int4"
      },
      {
        "ordinal": 8,
        "name": "expires_at",
        "type_info": "Timestamptz"
      },
      {
        "ordinal": 9,
        "name": "last_polled_at",
        "type_info": "Timestamptz"
      },
      {
        "ordinal": 10,
        "name": "created_at",
        "type_info": "Timestamptz"
      }
    ],
    "parameters": {
      "Left": [
        "Text",
        "Timestamptz"
      ]
    },
    "nullable": [
      false,
      false,
      false,
      false,
      true,
      true,
      false,
      false,
      false,
      true,
      false
    ]
  },
  "hash": "a9b8705c219a8601e68f7ef258f8a0ac3c49daeb026b109d8d41d67d87b9db44"
}
