{
  "db_name": "SQLite",
  "query": "SELECT id, user_id, ip_address, user_agent, expires_at, created_at FROM yauth_sessions WHERE token_hash = ? /* sqlite */",
  "describe": {
    "columns": [
      {
        "name": "id",
        "ordinal": 0,
        "type_info": "Text"
      },
      {
        "name": "user_id",
        "ordinal": 1,
        "type_info": "Text"
      },
      {
        "name": "ip_address",
        "ordinal": 2,
        "type_info": "Text"
      },
      {
        "name": "user_agent",
        "ordinal": 3,
        "type_info": "Text"
      },
      {
        "name": "expires_at",
        "ordinal": 4,
        "type_info": "Text"
      },
      {
        "name": "created_at",
        "ordinal": 5,
        "type_info": "Text"
      }
    ],
    "parameters": {
      "Right": 1
    },
    "nullable": [
      true,
      false,
      true,
      true,
      false,
      false
    ]
  },
  "hash": "3d0b81d1f6781de130ea907bdcec98be37db606201a8c97ade7d3359c9814b80"
}
